grafton/__init__.py
grafton/anonymiser.py
grafton-0.1.9.dist-info/LICENSE
grafton-0.1.9.dist-info/METADATA
grafton-0.1.9.dist-info/WHEEL
grafton-0.1.9.dist-info/top_level.txt
grafton-0.1.9.dist-info/RECORD
