Metadata-Version: 2.1
Name: grafton
Version: 0.1.9
Summary: grafton anonymises data in any input file using an encoding key and informed consent list.
Home-page: https://github.com/yForecasting/grafton
Author: Yves R. Sagaert
Author-email: yves.r.sagaert@gmail.com
License: GNU GPLv3
Classifier: Development Status :: 4 - Beta
Classifier: License :: OSI Approved :: GNU General Public License v3 (GPLv3)
Classifier: Programming Language :: Python
Classifier: Programming Language :: Python :: 3.5
Classifier: Programming Language :: Python :: 3.6
Classifier: Topic :: Software Development :: Libraries
Classifier: Topic :: Software Development :: Libraries :: Python Modules
Classifier: Intended Audience :: Developers
Requires-Python: >=3.5
License-File: LICENSE
Requires-Dist: pandas
